{
  "version": "1.0",
  "saved_at": "2025-11-08T10:58:50.045909",
  "fact_count": 1,
  "facts": [
    {
      "fact": "This is a list of college football teams by the number of weeks they have been ranked number one in the AP poll since its inception in 1936 through November 2, 2025.\n\n† No longer a FBS school.\nBold: Team ranked number one in most recent poll.",
      "timestamp": "2025-11-08T10:58:50.044688",
      "category": "biography",
      "confidence": 0.95,
      "source": "wikipedia",
      "metadata": {},
      "is_outdated": false
    }
  ]
}